onerun/__init__.py
onerun/_client.py
onerun/_resource.py
onerun/_types.py
onerun/_version.py
onerun/py.typed
onerun/_utils/__init__.py
onerun/_utils/_transform.py
onerun/connect/__init__.py
onerun/connect/types.py
onerun/connect/worker.py
onerun/resources/__init__.py
onerun/resources/simulations/__init__.py
onerun/resources/simulations/conversations.py
onerun/resources/simulations/simulations.py
onerun/types/__init__.py
onerun/types/agents.py
onerun/types/common.py
onerun/types/conversations.py
onerun/types/objectives.py
onerun/types/responses.py
onerun/types/simulations.py
onerun-0.1.0.dist-info/METADATA
onerun-0.1.0.dist-info/WHEEL
onerun-0.1.0.dist-info/RECORD
