Metadata-Version: 2.3
Name: onerun
Version: 0.1.0
Summary: OneRun python SDK
Author: OneRun.ai
Requires-Python: >=3.10
Requires-Dist: apscheduler==4.0.0a6
Requires-Dist: fastapi>=0.116.1
Requires-Dist: httpx>=0.28.1
Requires-Dist: pydantic>=2.11.7
Requires-Dist: uvicorn>=0.35.0
